Assignment 1/G1R_200204_200341_201050_A1/A1Q1_one_bit_full_adder.v
module one_bit_full_adder(C_out,S,A,B,C_in);

    input A,B,C_in;
    output C_out,S;

    assign S=(A^B)^C_in;
    assign C_out=(A&B)|(B&C_in)|(C_in&A);

endmodule

Assignment 1/G1R_200204_200341_201050/A1Q1_eight_bit_ripple_carry_adder.v
`include "A1Q1_one_bit_full_adder.v"

module eight_bit_ripple_carry_adder(C_out,S,A,B,C_in);
    input [7:0] A;
    input [7:0] B;
    input C_in;
    output C_out;
    output [7:0] S;
    wire w[6:0]; // 6 wires for transferring C_out to C_in of next adder
    one_bit_full_adder f1(w[0],S[0],A[0],B[0],C_in);
    one_bit_full_adder f2(w[1],S[1],A[1],B[1],w[0]);
    one_bit_full_adder f3(w[2],S[2],A[2],B[2],w[1]);
    one_bit_full_adder f4(w[3],S[3],A[3],B[3],w[2]);
    one_bit_full_adder f5(w[4],S[4],A[4],B[4],w[3]);
    one_bit_full_adder f6(w[5],S[5],A[5],B[5],w[4]);
    one_bit_full_adder f7(w[6],S[6],A[6],B[6],w[5]);
    one_bit_full_adder f8(C_out,S[7],A[7],B[7],w[6]);
endmodule

Assignment 1/G1R_200204_200341_201050/A1Q1_eight_bit_ripple_carry_adder_tb.v
`timescale 1ns/1ns
`include  "A1Q1_eight_bit_ripple_carry_adder.v"
module A1Q1_eight_bit_ripple_carry_adder_tb;
reg [7:0] A;
reg [7:0] B;
reg C_in;
wire [7:0] S;
wire C_out;
integer i;
integer j;
eight_bit_ripple_carry_adder uut(C_out,S,A,B,C_in);
initial begin
    $dumpfile("A1Q1_eight_bit_ripple_carry_adder.vcd");
    $dumpvars(0, A1Q1_eight_bit_ripple_carry_adder_tb);
    A<=8'b0;
    B<=8'b0;
    C_in<=1'b0;
    #5;
    $monitor("%t A=%b, B=%b, Carry=%b, Sum=%b",$time,A,B,C_out,S);
end
initial begin
    for(i=0;i<4;i=i+1) begin 
        for(j=0;j<4;j=j+1) begin 
            #5 A<=i;B<=j;
        end
    end
end
endmodule

Assignment 1/G1R_200204_200341_201050/A1Q1_eight_bit_ripple_carry_adder.vcd
$date
	Mon Jan 24 09:32:34 2022
$end
$version
	Icarus Verilog
$end
$timescale
	1ns
$end
$scope module A1Q1_eight_bit_ripple_carry_adder_tb $end
$var wire 8 ! S [7:0] $end
$var wire 1 " C_out $end
$var reg 8 # A [7:0] $end
$var reg 8 $ B [7:0] $end
$var reg 1 % C_in $end
$var integer 32 & i [31:0] $end
$var integer 32 ' j [31:0] $end
$scope module uut $end
$var wire 8 ( A [7:0] $end
$var wire 8 ) B [7:0] $end
$var wire 1 % C_in $end
$var wire 8 * S [7:0] $end
$var wire 1 " C_out $end
$scope module f1 $end
$var wire 1 + A $end
$var wire 1 , B $end
$var wire 1 % C_in $end
$var wire 1 - C_out $end
$var wire 1 . S $end
$upscope $end
$scope module f2 $end
$var wire 1 / A $end
$var wire 1 0 B $end
$var wire 1 - C_in $end
$var wire 1 1 C_out $end
$var wire 1 2 S $end
$upscope $end
$scope module f3 $end
$var wire 1 3 A $end
$var wire 1 4 B $end
$var wire 1 1 C_in $end
$var wire 1 5 C_out $end
$var wire 1 6 S $end
$upscope $end
$scope module f4 $end
$var wire 1 7 A $end
$var wire 1 8 B $end
$var wire 1 5 C_in $end
$var wire 1 9 C_out $end
$var wire 1 : S $end
$upscope $end
$scope module f5 $end
$var wire 1 ; A $end
$var wire 1 < B $end
$var wire 1 9 C_in $end
$var wire 1 = C_out $end
$var wire 1 > S $end
$upscope $end
$scope module f6 $end
$var wire 1 ? A $end
$var wire 1 @ B $end
$var wire 1 = C_in $end
$var wire 1 A C_out $end
$var wire 1 B S $end
$upscope $end
$scope module f7 $end
$var wire 1 C A $end
$var wire 1 D B $end
$var wire 1 A C_in $end
$var wire 1 E C_out $end
$var wire 1 F S $end
$upscope $end
$scope module f8 $end
$var wire 1 G A $end
$var wire 1 H B $end
$var wire 1 E C_in $end
$var wire 1 " C_out $end
$var wire 1 I S $end
$upscope $end
$upscope $end
$upscope $end
$enddefinitions $end
#0
$dumpvars
0I
0H
0G
0F
0E
0D
0C
0B
0A
0@
0?
0>
0=
0<
0;
0:
09
08
07
06
05
04
03
02
01
00
0/
0.
0-
0,
0+
b0 *
b0 )
b0 (
b0 '
b0 &
0%
b0 $
b0 #
0"
b0 !
$end
#5
b1 '
#10
b1 !
b1 *
1.
1,
b1 $
b1 )
b10 '
#15
0.
b10 !
b10 *
12
0,
10
b10 $
b10 )
b11 '
#20
b11 !
b11 *
1.
1,
b11 $
b11 )
b1 &
b0 '
#25
b1 !
b1 *
02
0,
00
1+
b0 $
b0 )
b1 #
b1 (
b1 '
#30
12
1-
b10 !
b10 *
0.
1,
b1 $
b1 )
b10 '
#35
06
0-
01
1.
b11 !
b11 *
12
0,
10
b10 $
b10 )
b11 '
#40
16
11
02
1-
b100 !
b100 *
0.
1,
b11 $
b11 )
b10 &
b0 '
#45
06
01
b10 !
b10 *
12
0-
0,
00
0+
1/
b0 $
b0 )
b10 #
b10 (
b1 '
#50
b11 !
b11 *
1.
1,
b1 $
b1 )
b10 '
#55
16
11
0.
b100 !
b100 *
02
0,
10
b10 $
b10 )
b11 '
#60
b101 !
b101 *
1.
1,
b11 $
b11 )
b11 &
b0 '
#65
06
01
b11 !
b11 *
12
0,
00
1+
b0 $
b0 )
b11 #
b11 (
b1 '
#70
16
11
02
1-
b100 !
b100 *
0.
1,
b1 $
b1 )
b10 '
#75
0-
1.
b101 !
b101 *
02
0,
10
b10 $
b10 )
b11 '
#80
12
1-
b110 !
b110 *
0.
1,
b11 $
b11 )
b100 &
b100 '
