Assignment 1/G1R_200204_200341_201050_A1/A1Q3_three_to_eight_decoder.v
/*
Write a Verilog code to implement a two-to-four decoder. Then a top
module for three-to-eight decoder using two-to-four decoder. Write a test
bench to test three-to eight decoder for all possible input with five-time
delay.
*/

module three_to_eight_decoder(B2,B1,B0,enable,P7,P6,P5,P4,P3,P2,P1,P0);
    input B2,B1,B0,enable;
    output P7,P6,P5,P4,P3,P2,P1,P0;
    wire D0,D1,D2,D3;
    wire zer_net=1'b0;
    two_to_four_decoder decode1(zer_net,B2,enable,D3,D2,D1,D0);
    two_to_four_decoder decode2(B1,B0,D0,P3,P2,P1,P0);
    two_to_four_decoder decode3(B1,B0,D1,P7,P6,P5,P4);
endmodule;


module two_to_four_decoder(A1, A0, enable, Y3, Y2, Y1, Y0);
input A1,A0,enable;
output reg Y3,Y2,Y1,Y0;
wire C3,C2,C1,C0;
wire nA1,nA0;
not n1(nA1,A1);
not n2(nA0,A0);
and a1(C3,A1,A0);
and a2(C2,A1,nA0);
and a3(C1,nA1,A0);
and a4(C0,nA1,nA0);
always @(*)
    if(enable==0)
        begin
            Y3<=1'b0;
            Y2<=1'b0;
            Y1<=1'b0;
            Y0<=1'b0;
        end 
    else 
        begin
            Y3 <= C3;
            Y2 <= C2;
            Y1 <= C1;
            Y0 <= C0;
            
        end
endmodule

Assignment 1/G1R_200204_200341_201050/A1Q3_three_to_eight_decoder_tb.v
`timescale 1ns/1ns
`include "A1Q3_three_to_eight_decoder.v"

module three_to_eight_decoder_tb;
reg enable,A0,A1,A2;
integer i;
wire Y7,Y6,Y5,Y4,Y3,Y2,Y1,Y0;
three_to_eight_decoder uut(A2,A1,A0,enable,Y7,Y6,Y5,Y4,Y3,Y2,Y1,Y0);
initial begin
    $dumpfile("A1Q3_three_to_eight_decoder_tb.vcd");
    $dumpvars(0, three_to_eight_decoder_tb);
    A0<=1'b0;
    A1<=1'b0;
    A2<=1'b0;
    enable<=1'b0;
    #5;
    $monitor("%t Enable=%0b A2=%0b A1=%0b A0=%0b Y7=%0b Y6=%0b Y5=%0b Y4=%0b Y3=%0b Y2=%0b Y1=%0b Y0=%0b",$time,enable, A2,A1,A0,Y7,Y6,Y5,Y4,Y3,Y2,Y1,Y0);
    for(i=0;i<16;i=i+1) begin
        #5 {enable,A2,A1,A0}=i;
    end
    #85 $display("Test complete");
end

endmodule

Assignment 1/G1R_200204_200341_201050/A1Q3_three_to_eight_decoder_tb.vcd
$date
	Mon Jan 24 09:47:29 2022
$end
$version
	Icarus Verilog
$end
$timescale
	1ns
$end
$scope module three_to_eight_decoder_tb $end
$var wire 1 ! Y7 $end
$var wire 1 " Y6 $end
$var wire 1 # Y5 $end
$var wire 1 $ Y4 $end
$var wire 1 % Y3 $end
$var wire 1 & Y2 $end
$var wire 1 ' Y1 $end
$var wire 1 ( Y0 $end
$var reg 1 ) A0 $end
$var reg 1 * A1 $end
$var reg 1 + A2 $end
$var reg 1 , enable $end
$var integer 32 - i [31:0] $end
$scope module uut $end
$var wire 1 ) B0 $end
$var wire 1 * B1 $end
$var wire 1 + B2 $end
$var wire 1 , enable $end
$var wire 1 . zer_net $end
$var wire 1 ! P7 $end
$var wire 1 " P6 $end
$var wire 1 # P5 $end
$var wire 1 $ P4 $end
$var wire 1 % P3 $end
$var wire 1 & P2 $end
$var wire 1 ' P1 $end
$var wire 1 ( P0 $end
$var wire 1 / D3 $end
$var wire 1 0 D2 $end
$var wire 1 1 D1 $end
$var wire 1 2 D0 $end
$scope module decode1 $end
$var wire 1 + A0 $end
$var wire 1 . A1 $end
$var wire 1 3 C0 $end
$var wire 1 4 C1 $end
$var wire 1 5 C2 $end
$var wire 1 6 C3 $end
$var wire 1 , enable $end
$var wire 1 7 nA0 $end
$var wire 1 8 nA1 $end
$var reg 1 2 Y0 $end
$var reg 1 1 Y1 $end
$var reg 1 0 Y2 $end
$var reg 1 / Y3 $end
$upscope $end
$scope module decode2 $end
$var wire 1 ) A0 $end
$var wire 1 * A1 $end
$var wire 1 9 C0 $end
$var wire 1 : C1 $end
$var wire 1 ; C2 $end
$var wire 1 < C3 $end
$var wire 1 2 enable $end
$var wire 1 = nA0 $end
$var wire 1 > nA1 $end
$var reg 1 ( Y0 $end
$var reg 1 ' Y1 $end
$var reg 1 & Y2 $end
$var reg 1 % Y3 $end
$upscope $end
$scope module decode3 $end
$var wire 1 ) A0 $end
$var wire 1 * A1 $end
$var wire 1 ? C0 $end
$var wire 1 @ C1 $end
$var wire 1 A C2 $end
$var wire 1 B C3 $end
$var wire 1 1 enable $end
$var wire 1 C nA0 $end
$var wire 1 D nA1 $end
$var reg 1 $ Y0 $end
$var reg 1 # Y1 $end
$var reg 1 " Y2 $end
$var reg 1 ! Y3 $end
$upscope $end
$upscope $end
$upscope $end
$enddefinitions $end
#0
$dumpvars
1D
1C
0B
0A
0@
1?
1>
1=
0<
0;
0:
19
18
17
06
05
04
13
02
01
00
0/
0.
bx -
0,
0+
0*
0)
0(
0'
0&
0%
0$
0#
0"
0!
$end
#5
b0 -
#10
b1 -
#15
09
0?
0=
1:
0C
1@
b10 -
1)
#20
0>
1;
0D
1A
1=
0:
1C
0@
b11 -
1*
0)
#25
0;
0A
0=
1<
0C
1B
b100 -
1)
#30
03
19
1?
07
14
1>
1D
1=
0<
1C
0B
b101 -
1+
0*
0)
#35
09
0?
0=
1:
0C
1@
b110 -
1)
#40
0>
1;
0D
1A
1=
0:
1C
0@
b111 -
1*
0)
#45
0;
0A
0=
1<
0C
1B
b1000 -
1)
#50
1(
12
13
19
1?
17
04
1>
1D
1=
0<
1C
0B
b1001 -
1,
0+
0*
0)
#55
0(
1'
09
0?
0=
1:
0C
1@
b1010 -
1)
#60
0'
1&
0>
1;
0D
1A
1=
0:
1C
0@
b1011 -
1*
0)
#65
0&
1%
0;
0A
0=
1<
0C
1B
b1100 -
1)
#70
1$
02
0(
11
0%
03
19
1?
07
14
1>
1D
1=
0<
1C
0B
b1101 -
1+
0*
0)
#75
0$
1#
09
0?
0=
1:
0C
1@
b1110 -
1)
#80
0#
1"
0>
1;
0D
1A
1=
0:
1C
0@
b1111 -
1*
0)
#85
0"
1!
0;
0A
0=
1<
0C
1B
b10000 -
1)
