Assignment 1/Question 3/three_to_eight.v
/*
Write a Verilog code to implement a two-to-four decoder. Then a top
module for three-to-eight decoder using two-to-four decoder. Write a test
bench to test three-to eight decoder for all possible input with five-time
delay.
*/

module three_to_eight(B2,B1,B0,enable,P7,P6,P5,P4,P3,P2,P1,P0);
    input B2,B1,B0,enable;
    output P7,P6,P5,P4,P3,P2,P1,P0;
    wire D0,D1,D2,D3;
    wire zer_net=1'b0;
    two_to_four decode1(zer_net,B2,enable,D3,D2,D1,D0);
    two_to_four decode2(B1,B0,D0,P3,P2,P1,P0);
    two_to_four decode3(B1,B0,D1,P7,P6,P5,P4);
endmodule;


module two_to_four(A1, A0, enable, Y3, Y2, Y1, Y0);
input A1,A0,enable;
output reg Y3,Y2,Y1,Y0;
wire C3,C2,C1,C0;
wire nA1,nA0;
not n1(nA1,A1);
not n2(nA0,A0);
and a1(C3,A1,A0);
and a2(C2,A1,nA0);
and a3(C1,nA1,A0);
and a4(C0,nA1,nA0);
always @(A1,A0,enable)
    if(enable==0)
        begin
            Y3<=1'b0;
            Y2<=1'b0;
            Y1<=1'b0;
            Y0<=1'b0;
        end 
    else 
        begin
            Y3 <= C3;
            Y2 <= C2;
            Y1 <= C1;
            Y0 <= C0;
            
        end
endmodule

Assignment 1/Question 3/three_to_eight_tb.v
`timescale 1ns/1ns
`include "three_to_eight.v"

module three_to_eight_tb;
reg enable,A0,A1,A2;
integer i;
wire Y7,Y6,Y5,Y4,Y3,Y2,Y1,Y0;
three_to_eight uut(A2,A1,A0,enable,Y7,Y6,Y5,Y4,Y3,Y2,Y1,Y0);
initial begin
    $dumpfile("three_to_eight_tb.vcd");
    $dumpvars(0, three_to_eight_tb);
    A0<=1'b0;
    A1<=1'b0;
    A2<=1'b0;
    enable<=1'b0;
    $monitor("Enable=%0b A2=%0b A1=%0b A0=%0b Y7=%0b Y6=%0b Y5=%0b Y4=%0b Y3=%0b Y2=%0b Y1=%0b Y0=%0b",enable, A2,A1,A0,Y7,Y6,Y5,Y4,Y3,Y2,Y1,Y0);
    for(i=0;i<16;i=i+1) begin
        #10 {enable,A2,A1,A0}<=i;
    end
    #170 $display("Test complete");
end

endmodule

Assignment 1/Question 3/three_to_eight_tb.vcd
$date
	Tue Jan 18 21:31:02 2022
$end
$version
	Icarus Verilog
$end
$timescale
	1ns
$end
$scope module three_to_eight_tb $end
$var wire 1 ! Y7 $end
$var wire 1 " Y6 $end
$var wire 1 # Y5 $end
$var wire 1 $ Y4 $end
$var wire 1 % Y3 $end
$var wire 1 & Y2 $end
$var wire 1 ' Y1 $end
$var wire 1 ( Y0 $end
$var reg 1 ) A0 $end
$var reg 1 * A1 $end
$var reg 1 + A2 $end
$var reg 1 , enable $end
$var integer 32 - i [31:0] $end
$scope module uut $end
$var wire 1 ) B0 $end
$var wire 1 * B1 $end
$var wire 1 + B2 $end
$var wire 1 , enable $end
$var wire 1 . zer_net $end
$var wire 1 ! P7 $end
$var wire 1 " P6 $end
$var wire 1 # P5 $end
$var wire 1 $ P4 $end
$var wire 1 % P3 $end
$var wire 1 & P2 $end
$var wire 1 ' P1 $end
$var wire 1 ( P0 $end
$var wire 1 / D3 $end
$var wire 1 0 D2 $end
$var wire 1 1 D1 $end
$var wire 1 2 D0 $end
$scope module decode1 $end
$var wire 1 + A0 $end
$var wire 1 . A1 $end
$var wire 1 3 C0 $end
$var wire 1 4 C1 $end
$var wire 1 5 C2 $end
$var wire 1 6 C3 $end
$var wire 1 , enable $end
$var wire 1 7 nA0 $end
$var wire 1 8 nA1 $end
$var reg 1 2 Y0 $end
$var reg 1 1 Y1 $end
$var reg 1 0 Y2 $end
$var reg 1 / Y3 $end
$upscope $end
$scope module decode2 $end
$var wire 1 ) A0 $end
$var wire 1 * A1 $end
$var wire 1 9 C0 $end
$var wire 1 : C1 $end
$var wire 1 ; C2 $end
$var wire 1 < C3 $end
$var wire 1 2 enable $end
$var wire 1 = nA0 $end
$var wire 1 > nA1 $end
$var reg 1 ( Y0 $end
$var reg 1 ' Y1 $end
$var reg 1 & Y2 $end
$var reg 1 % Y3 $end
$upscope $end
$scope module decode3 $end
$var wire 1 ) A0 $end
$var wire 1 * A1 $end
$var wire 1 ? C0 $end
$var wire 1 @ C1 $end
$var wire 1 A C2 $end
$var wire 1 B C3 $end
$var wire 1 1 enable $end
$var wire 1 C nA0 $end
$var wire 1 D nA1 $end
$var reg 1 $ Y0 $end
$var reg 1 # Y1 $end
$var reg 1 " Y2 $end
$var reg 1 ! Y3 $end
$upscope $end
$upscope $end
$upscope $end
$enddefinitions $end
#0
$dumpvars
1D
1C
0B
0A
0@
1?
1>
1=
0<
0;
0:
19
18
17
06
05
04
13
02
01
00
0/
0.
b0 -
0,
0+
0*
0)
0(
0'
0&
0%
0$
0#
0"
0!
$end
#10
b1 -
#20
09
0?
0=
1:
0C
1@
1)
b10 -
#30
0>
1;
0D
1A
1=
0:
1C
0@
1*
0)
b11 -
#40
0;
0A
0=
1<
0C
1B
1)
b100 -
#50
03
19
1?
07
14
1>
1D
1=
0<
1C
0B
1+
0*
0)
b101 -
#60
09
0?
0=
1:
0C
1@
1)
b110 -
#70
0>
1;
0D
1A
1=
0:
1C
0@
1*
0)
b111 -
#80
0;
0A
0=
1<
0C
1B
1)
b1000 -
#90
1$
11
13
19
1?
17
04
1>
1D
1=
0<
1C
0B
1,
0+
0*
0)
b1001 -
#100
09
0?
0=
1:
0C
1@
1)
b1010 -
#110
0$
1#
0>
1;
0D
1A
1=
0:
1C
0@
1*
0)
b1011 -
#120
0#
1"
0;
0A
0=
1<
0C
1B
1)
b1100 -
#130
1(
12
01
0"
0!
03
19
1?
07
14
1>
1D
1=
0<
1C
0B
1+
0*
0)
b1101 -
#140
09
0?
0=
1:
0C
1@
1)
b1110 -
#150
0(
1'
0>
1;
0D
1A
1=
0:
1C
0@
1*
0)
b1111 -
#160
0'
1&
0;
0A
0=
1<
0C
1B
1)
b10000 -
